<annotation>
	<folder></folder>
	<filename>20200828_105624_jpg.rf.be33479a9ca9ed3c2fd4ba51b619362e.jpg</filename>
	<path>20200828_105624_jpg.rf.be33479a9ca9ed3c2fd4ba51b619362e.jpg</path>
	<source>
		<database>roboflow.ai</database>
	</source>
	<size>
		<width>640</width>
		<height>480</height>
		<depth>3</depth>
	</size>
	<segmented>0</segmented>
	<object>
		<name>right</name>
		<pose>Unspecified</pose>
		<truncated>0</truncated>
		<difficult>0</difficult>
		<occluded>0</occluded>
		<bndbox>
			<xmin>122</xmin>
			<xmax>208</xmax>
			<ymin>148</ymin>
			<ymax>407</ymax>
		</bndbox>
	</object>
</annotation>
