<annotation>
	<folder></folder>
	<filename>resized_IMG_7898_JPG.rf.2efa344a1ea1f0f6a0eb0c5c9d8b46fd.jpg</filename>
	<path>resized_IMG_7898_JPG.rf.2efa344a1ea1f0f6a0eb0c5c9d8b46fd.jpg</path>
	<source>
		<database>roboflow.ai</database>
	</source>
	<size>
		<width>640</width>
		<height>480</height>
		<depth>3</depth>
	</size>
	<segmented>0</segmented>
	<object>
		<name>up</name>
		<pose>Unspecified</pose>
		<truncated>0</truncated>
		<difficult>0</difficult>
		<occluded>0</occluded>
		<bndbox>
			<xmin>277</xmin>
			<xmax>412</xmax>
			<ymin>23</ymin>
			<ymax>167</ymax>
		</bndbox>
	</object>
</annotation>
