<annotation>
	<folder></folder>
	<filename>resized_IMG_6469_JPG.rf.92da58c14e7c30312ba955f7f9d8fd98.jpg</filename>
	<path>resized_IMG_6469_JPG.rf.92da58c14e7c30312ba955f7f9d8fd98.jpg</path>
	<source>
		<database>roboflow.ai</database>
	</source>
	<size>
		<width>640</width>
		<height>480</height>
		<depth>3</depth>
	</size>
	<segmented>0</segmented>
	<object>
		<name>8</name>
		<pose>Unspecified</pose>
		<truncated>0</truncated>
		<difficult>0</difficult>
		<occluded>0</occluded>
		<bndbox>
			<xmin>308</xmin>
			<xmax>533</xmax>
			<ymin>173</ymin>
			<ymax>376</ymax>
		</bndbox>
	</object>
</annotation>
