<annotation>
	<folder></folder>
	<filename>resized_IMG_6450_JPG.rf.839976df5f0ac70a755aa9896df96653.jpg</filename>
	<path>resized_IMG_6450_JPG.rf.839976df5f0ac70a755aa9896df96653.jpg</path>
	<source>
		<database>roboflow.ai</database>
	</source>
	<size>
		<width>640</width>
		<height>480</height>
		<depth>3</depth>
	</size>
	<segmented>0</segmented>
	<object>
		<name>z</name>
		<pose>Unspecified</pose>
		<truncated>0</truncated>
		<difficult>0</difficult>
		<occluded>0</occluded>
		<bndbox>
			<xmin>165</xmin>
			<xmax>388</xmax>
			<ymin>137</ymin>
			<ymax>319</ymax>
		</bndbox>
	</object>
</annotation>
