<annotation>
	<folder></folder>
	<filename>16--2-_jpeg.rf.72acfef16be64b535398fe8a72b4d7c3.jpg</filename>
	<path>16--2-_jpeg.rf.72acfef16be64b535398fe8a72b4d7c3.jpg</path>
	<source>
		<database>roboflow.ai</database>
	</source>
	<size>
		<width>416</width>
		<height>416</height>
		<depth>3</depth>
	</size>
	<segmented>0</segmented>
	<object>
		<name>down</name>
		<pose>Unspecified</pose>
		<truncated>0</truncated>
		<difficult>0</difficult>
		<occluded>0</occluded>
		<bndbox>
			<xmin>180</xmin>
			<xmax>314</xmax>
			<ymin>130</ymin>
			<ymax>320</ymax>
		</bndbox>
	</object>
</annotation>
