<annotation>
	<folder></folder>
	<filename>resized_IMG_7449_JPG.rf.5909ba828a37e9195cde266ae888693b.jpg</filename>
	<path>resized_IMG_7449_JPG.rf.5909ba828a37e9195cde266ae888693b.jpg</path>
	<source>
		<database>roboflow.ai</database>
	</source>
	<size>
		<width>416</width>
		<height>416</height>
		<depth>3</depth>
	</size>
	<segmented>0</segmented>
	<object>
		<name>8</name>
		<pose>Unspecified</pose>
		<truncated>0</truncated>
		<difficult>0</difficult>
		<occluded>0</occluded>
		<bndbox>
			<xmin>172</xmin>
			<xmax>247</xmax>
			<ymin>62</ymin>
			<ymax>204</ymax>
		</bndbox>
	</object>
</annotation>
